Workbook

Sheet Part1-Individual
A1: You are part of a financial consulting team tasked with advising a startup client looking to invest in one of three diversified investment portfolios.
A2: Each portfolio has various potential outcomes, probabilities, associated risks, and strategic implications. Your goal is to analyze these portfolios in depth and provide a well-justified recommendation.
A4: Investment Portfolios Overview
A6: Portfolio | B6: Growth Outcome | C6: Payoff ($) | D6: Probability
A7: A | B7: High | C7: 300000 | D7: 0.2
B8: Moderate | C8: 120000 | D8: 0.5
B9: Low | C9: 30000 | D9: 0.25
B10: Total Loss | C10: -100000 | D10: 0.05
A11: B | B11: High | C11: 400000 | D11: 0.15
B12: Moderate | C12: 150000 | D12: 0.5
B13: Low | C13: 50000 | D13: 0.25
B14: Total Loss | C14: -80000 | D14: 0.1
A15: C | B15: High | C15: 250000 | D15: 0.25
B16: Moderate | C16: 90000 | D16: 0.5
B17: Low | C17: 20000 | D17: 0.15
B18: Total Loss | C18: -60000 | D18: 0.1
A20: Part 1: Detailed Individual Analysis - will not be graded but must be submitted prior to joining a group
A21: Before joining a group, you must gain a comprehensive understanding of each portfolio.
A23: Tasks
A24: 1. Calculate the Payoff Strategies for each investment option using Risk Modelling as you learned in class.
B26: For each type of decision-making, create a table for each portfolio.
A28: 2. Sensitivity Analysis: Assess how sensitive the average payoff is to changes in the probability of the high-growth scenario (e.g., what happens if the probability increases or decreases by 10% between 10 to 90%).
A31: Investment Decision Analysis Using Risk Modelling
A33: A startup company is evaluating three investment portfolios (A, B, and C) under uncertain market conditions. Each portfolio has different payoffs and probabilities across four possible growth outcomes:
A35: High Growth
A36: Moderate Growth
A37: Low Growth
A38: Total Loss
A42: 🔹 Part 1: Quantitative Analysis
A44: 1. Risk Modelling & Payoff Analysis
A46: For each portfolio:
A48: Calculate:
A49: Expected Payoff (Expected Value)
... A122: Plot graphs and interpret results

Sheet Final
A1: 1. Calculate the Payoff Strategies for each investment option using Risk Modelling as you learned in class.
A3: Portfolio | B3: Growth Outcome | C3: Payoff ($) | D3: Probability | E3: Average Payoff ($) | F3: Expected Payoff ($) | G3: (Payoff-expected)^2 * probability | H3: Variance | I3: Standard Deviation | J3: Return to risk Ratio
A4: A | B4: High | C4: 300000 | D4: 0.2 | E4: =C4*D4 -> 60000 | F4: =SUM(E4:E7) -> 122500 | G4: =((C4-$F$4)^2 *D4) -> 6301250000 | H4: =SUM(G4:G7) -> 10918750000 | I4: =SQRT(H4) -> 104492.82 | J4: =F4/I4 -> 1.1723293
B5: Moderate | C5: 120000 | D5: 0.5 | E5: =C5*D5 -> 60000 | G5: =((C5-$F$4)^2 *D5) -> 3125000
B6: Low | C6: 30000 | D6: 0.25 | E6: =C6*D6 -> 7500 | G6: =((C6-$F$4)^2 *D6) -> 2139062500
B7: Total Loss | C7: -100000 | D7: 0.05 | E7: =C7*D7 -> -5000 | G7: =((C7-$F$4)^2 *D7) -> 2475312500
A9: Portfolio | B9: Growth Outcome | C9: Payoff ($) | D9: Probability | E9: Average Payoff ($) | F9: Expected Payoff | G9: (Payoff-expected)^2 * probability | H9: Variance | I9: Standard Deviation | J9: Return to risk Ratio
A10: B | B10: High | C10: 400000 | D10: 0.15 | E10: =C10*D10 -> 60000 | F10: =SUM(E10:E13) -> 139500 | G10: =(C10-$F$10)^2 *D10 -> 10179037500 | H10: =SUM(G10:G13) -> 17054750000 | I10: =SQRT(H10) -> 130593.84 | J10: =F10/I10 -> 1.0681974 | L10: Best Expected Payoff ($) (B) | M10: =MAX(F4,F10,F16) -> 139500
B11: Moderate | C11: 150000 | D11: 0.5 | E11: =C11*D11 -> 75000 | G11: =(C11-$F$10)^2 *D11 -> 55125000 | L11: Opportunity Loss (Portfolio A) | M11: =F4-M10 -> -17000
B12: Low | C12: 50000 | D12: 0.25 | E12: =C12*D12 -> 12500 | G12: =(C12-$F$10)^2 *D12 -> 2002562500 | L12: Opportunity Loss (Portfolio C) | M12: =F16-M10 -> -35000
B13: Total Loss | C13: -80000 | D13: 0.1 | E13: =C13*D13 -> -8000 | G13: =(C13-$F$10)^2 *D13 -> 4818025000 | L13: Least Risk Portfolio (Portfolio C) | M13: =I16 -> 95784.915
A15: Portfolio | B15: Growth Outcome | C15: Payoff ($) | D15: Probability | E15: Average Payoff ($) | F15: Expected Payoff | G15: (Payoff-expected)^2 * probability | H15: Variance | I15: Standard Deviation | J15: Return to risk Ratio
A16: C | B16: High | C16: 250000 | D16: 0.25 | E16: =C16*D16 -> 62500 | F16: =SUM(E16:E19) -> 104500 | G16: =(C16-$F$16)^2 *D16 -> 5292562500 | H16: =SUM(G16:G19) -> 9174750000 | I16: =SQRT(H16) -> 95784.915 | J16: =F16/I16 -> 1.090986
B17: Moderate | C17: 90000 | D17: 0.5 | E17: =C17*D17 -> 45000 | G17: =(C17-$F$16)^2 *D17 -> 105125000
B18: Low | C18: 20000 | D18: 0.15 | E18: =C18*D18 -> 3000 | G18: =(C18-$F$16)^2 *D18 -> 1071037500
B19: Total Loss | C19: -60000 | D19: 0.1 | E19: =C19*D19 -> -6000 | G19: =(C19-$F$16)^2 *D19 -> 2706025000
A21: 2. Sensitivity Analysis: Assess how sensitive the average payoff is to changes in the probability of the high-growth scenario (e.g., what happens if the probability increases or decreases by 10% between 10 to 90%).
A23: 10% increase and decrease
A24: Portfolio | B24: Growth Outcome | C24: Payoff ($) | D24: Probability | E24: 10% + | F24: 10% - | G24: Average Payoff (10% +) | H24: Average Payoff (Actual) | I24: Average Payoff (10% -) | J24: Expected Payoff (10% +) | K24: Expected Payoff (Actual) | L24: Expected Payoff (10% -)
A25: A | B25: High | C25: 300000 | D25: 0.2 | E25: =D25+0.1 -> 0.3 | F25: =D25-0.1 -> 0.1 | G25: =C25*E25 -> 90000 | H25: =C25*D25 -> 60000 | I25: =C25*F25 -> 30000 | J25: =SUM(G25:G28) -> 144687.5 | K25: =SUM(H25:H28) -> 122500 | L25: =SUM(I25:I28) -> 100312.5
B26: Moderate | C26: 120000 | D26: 0.5 | E26: =$D26*((1-E$25)/SUM($D$26:$D$28)) -> 0.4375 | F26: =$D26*((1-F$25)/SUM($D$26:$D$28)) -> 0.5625 | G26: =C26*E26 -> 52500 | H26: =C26*D26 -> 60000 | I26: =C26*F26 -> 67500
B27: Low | C27: 30000 | D27: 0.25 | E27: =$D27*((1-E$25)/SUM($D$26:$D$28)) -> 0.21875 | F27: =$D27*((1-F$25)/SUM($D$26:$D$28)) -> 0.28125 | G27: =C27*E27 -> 6562.5 | H27: =C27*D27 -> 7500 | I27: =C27*F27 -> 8437.5
B28: Total Loss | C28: -100000 | D28: 0.05 | E28: =$D28*((1-E$25)/SUM($D$26:$D$28)) -> 0.04375 | F28: =$D28*((1-F$25)/SUM($D$26:$D$28)) -> 0.05625 | G28: =C28*E28 -> -4375 | H28: =C28*D28 -> -5000 | I28: =C28*F28 -> -5625
A30: Portfolio | B30: Growth Outcome | C30: Payoff ($) | D30: Probability | E30: 10% + | F30: 10% - | G30: Average Payoff (10% +) | H30: Average Payoff (Actual) | I30: Average Payoff (10% -) | J30: Expected Payoff (10% +) | K30: Expected Payoff (Actual) | L30: Expected Payoff (10% -)
A31: B | B31: High | C31: 400000 | D31: 0.15 | E31: =D31+0.1 -> 0.25 | F31: =D31-0.1 -> 0.05 | G31: =C31*E31 -> 100000 | H31: =C31*D31 -> 60000 | I31: =C31*F31 -> 20000 | J31: =SUM(G31:G34) -> 170147.06 | K31: =SUM(H31:H34) -> 139500 | L31: =SUM(I31:I34) -> 108852.94
B32: Moderate | C32: 150000 | D32: 0.5 | E32: =$D32*((1-E$31)/SUM($D$32:$D$34)) -> 0.44117647 | F32: =$D32*((1-F$31)/SUM($D$32:$D$34)) -> 0.55882353 | G32: =C32*E32 -> 66176.471 | H32: =C32*D32 -> 75000 | I32: =C32*F32 -> 83823.529
B33: Low | C33: 50000 | D33: 0.25 | E33: =$D33*((1-E$31)/SUM($D$32:$D$34)) -> 0.22058824 | F33: =$D33*((1-F$31)/SUM($D$32:$D$34)) -> 0.27941176 | G33: =C33*E33 -> 11029.412 | H33: =C33*D33 -> 12500 | I33: =C33*F33 -> 13970.588
B34: Total Loss | C34: -80000 | D34: 0.1 | E34: =$D34*((1-E$31)/SUM($D$32:$D$34)) -> 0.088235294 | F34: =$D34*((1-F$31)/SUM($D$32:$D$34)) -> 0.11176471 | G34: =C34*E34 -> -7058.8235 | H34: =C34*D34 -> -8000 | I34: =C34*F34 -> -8941.1765
A36: Portfolio | B36: Growth Outcome | C36: Payoff ($) | D36: Probability | E36: 10% + | F36: 10% - | G36: Average Payoff (10% +) | H36: Average Payoff (Actual) | I36: Average Payoff (10% -) | J36: Expected Payoff (10% +) | K36: Expected Payoff (Actual) | L36: Expected Payoff (10% -)
A37: C | B37: High | C37: 250000 | D37: 0.25 | E37: =D37+0.1 -> 0.35 | F37: =D37-0.1 -> 0.15 | G37: =C37*E37 -> 87500 | H37: =C37*D37 -> 62500 | I37: =C37*F37 -> 37500 | J37: =SUM(G37:G40) -> 123900 | K37: =SUM(H37:H40) -> 104500 | L37: =SUM(I37:I40) -> 85100
B38: Moderate | C38: 90000 | D38: 0.5 | E38: =$D38*((1-E$37)/SUM($D$38:$D$40)) -> 0.43333333 | F38: =$D38*((1-F$37)/SUM($D$38:$D$40)) -> 0.56666667 | G38: =C38*E38 -> 39000 | H38: =C38*D38 -> 45000 | I38: =C38*F38 -> 51000
B39: Low | C39: 20000 | D39: 0.15 | E39: =$D39*((1-E$37)/SUM($D$38:$D$40)) -> 0.13 | F39: =$D39*((1-F$37)/SUM($D$38:$D$40)) -> 0.17 | G39: =C39*E39 -> 2600 | H39: =C39*D39 -> 3000 | I39: =C39*F39 -> 3400
B40: Total Loss | C40: -60000 | D40: 0.1 | E40: =$D40*((1-E$37)/SUM($D$38:$D$40)) -> 0.086666667 | F40: =$D40*((1-F$37)/SUM($D$38:$D$40)) -> 0.11333333 | G40: =C40*E40 -> -5200 | H40: =C40*D40 -> -6000 | I40: =C40*F40 -> -6800
A43: 20% increase and decrease
A44: Portfolio | B44: Growth Outcome | C44: Payoff ($) | D44: Probability | E44: 20% + | F44: 20% - | G44: Average Payoff (20% +) | H44: Average Payoff (Actual) | I44: Average Payoff (20% -) | J44: Expected Payoff (20% +) | K44: Expected Payoff (Actual) | L44: Expected Payoff (20% -)
A45: A | B45: High | C45: 300000 | D45: 0.2 | E45: =D45+0.2 -> 0.4 | F45: =D45-0.2 -> 0 | G45: =C45*E45 -> 120000 | H45: =C45*D45 -> 60000 | I45: =C45*F45 -> 0 | J45: =SUM(G45:G48) -> 166875 | K45: =SUM(H45:H48) -> 122500 | L45: =SUM(I45:I48) -> 78125
B46: Moderate | C46: 120000 | D46: 0.5 | E46: =$D46*((1-E$45)/SUM($D$46:$D$48)) -> 0.375 | F46: =$D46*((1-F$45)/SUM($D$46:$D$48)) -> 0.625 | G46: =C46*E46 -> 45000 | H46: =C46*D46 -> 60000 | I46: =C46*F46 -> 75000
B47: Low | C47: 30000 | D47: 0.25 | E47: =$D47*((1-E$45)/SUM($D$46:$D$48)) -> 0.1875 | F47: =$D47*((1-F$45)/SUM($D$46:$D$48)) -> 0.3125 | G47: =C47*E47 -> 5625 | H47: =C47*D47 -> 7500 | I47: =C47*F47 -> 9375
B48: Total Loss | C48: -100000 | D48: 0.05 | E48: =$D48*((1-E$45)/SUM($D$46:$D$48)) -> 0.0375 | F48: =$D48*((1-F$45)/SUM($D$46:$D$48)) -> 0.0625 | G48: =C48*E48 -> -3750 | H48: =C48*D48 -> -5000 | I48: =C48*F48 -> -6250
A50: Portfolio | B50: Growth Outcome | C50: Payoff ($) | D50: Probability | E50: 20% + | F50: 20% - | G50: Average Payoff (20% +) | H50: Average Payoff (Actual) | I50: Average Payoff (20% -) | J50: Expected Payoff (20% +) | K50: Expected Payoff (Actual) | L50: Expected Payoff (20% -)
A51: B | B51: High | C51: 400000 | D51: 0.15 | E51: =D51+0.2 -> 0.35 | F51: =D51-0.2 -> -0.05 | G51: =C51*E51 -> 140000 | H51: =C51*D51 -> 60000 | I51: =C51*F51 -> -20000 | J51: =SUM(G51:G54) -> 200794.12 | K51: =SUM(H51:H54) -> 139500 | L51: =SUM(I51:I54) -> 78205.882
B52: Moderate | C52: 150000 | D52: 0.5 | E52: =$D52*((1-E$51)/SUM($D$52:$D$54)) -> 0.38235294 | F52: =$D52*((1-F$51)/SUM($D$52:$D$54)) -> 0.61764706 | G52: =C52*E52 -> 57352.941 | H52: =C52*D52 -> 75000 | I52: =C52*F52 -> 92647.059
B53: Low | C53: 50000 | D53: 0.25 | E53: =$D53*((1-E$51)/SUM($D$52:$D$54)) -> 0.19117647 | F53: =$D53*((1-F$51)/SUM($D$52:$D$54)) -> 0.30882353 | G53: =C53*E53 -> 9558.8235 | H53: =C53*D53 -> 12500 | I53: =C53*F53 -> 15441.176
B54: Total Loss | C54: -80000 | D54: 0.1 | E54: =$D54*((1-E$51)/SUM($D$52:$D$54)) -> 0.076470588 | F54: =$D54*((1-F$51)/SUM($D$52:$D$54)) -> 0.12352941 | G54: =C54*E54 -> -6117.6471 | H54: =C54*D54 -> -8000 | I54: =C54*F54 -> -9882.3529
A56: Portfolio | B56: Growth Outcome | C56: Payoff ($) | D56: Probability | E56: 20% + | F56: 20% - | G56: Average Payoff (20% +) | H56: Average Payoff (Actual) | I56: Average Payoff (20% -) | J56: Expected Payoff (20% +) | K56: Expected Payoff (Actual) | L56: Expected Payoff (20% -)
A57: C | B57: High | C57: 250000 | D57: 0.25 | E57: =D57+0.2 -> 0.45 | F57: =D57-0.2 -> 0.05 | G57: =C57*E57 -> 112500 | H57: =C57*D57 -> 62500 | I57: =C57*F57 -> 12500 | J57: =SUM(G57:G60) -> 143300 | K57: =SUM(H57:H60) -> 104500 | L57: =SUM(I57:I60) -> 65700
B58: Moderate | C58: 90000 | D58: 0.5 | E58: =$D58*((1-E$57)/SUM($D$58:$D$60)) -> 0.36666667 | F58: =$D58*((1-F$57)/SUM($D$58:$D$60)) -> 0.63333333 | G58: =C58*E58 -> 33000 | H58: =C58*D58 -> 45000 | I58: =C58*F58 -> 57000
B59: Low | C59: 20000 | D59: 0.15 | E59: =$D59*((1-E$57)/SUM($D$58:$D$60)) -> 0.11 | F59: =$D59*((1-F$57)/SUM($D$58:$D$60)) -> 0.19 | G59: =C59*E59 -> 2200 | H59: =C59*D59 -> 3000 | I59: =C59*F59 -> 3800
B60: Total Loss | C60: -60000 | D60: 0.1 | E60: =$D60*((1-E$57)/SUM($D$58:$D$60)) -> 0.073333333 | F60: =$D60*((1-F$57)/SUM($D$58:$D$60)) -> 0.12666667 | G60: =C60*E60 -> -4400 | H60: =C60*D60 -> -6000 | I60: =C60*F60 -> -7600
A63: 30% increase and decrease
A64: Portfolio | B64: Growth Outcome | C64: Payoff ($) | D64: Probability | E64: 30% + | F64: 30% - | G64: Average Payoff (30% +) | H64: Average Payoff (Actual) | I64: Average Payoff (30% -) | J64: Expected Payoff (30% +) | K64: Expected Payoff (Actual) | L64: Expected Payoff (30% -)
A65: A | B65: High | C65: 300000 | D65: 0.2 | E65: =D65+0.3 -> 0.5 | F65: =D65-0.1 -> 0.1 | G65: =C65*E65 -> 150000 | H65: =C65*D65 -> 60000 | I65: =C65*F65 -> 30000 | J65: =SUM(G65:G68) -> 189062.5 | K65: =SUM(H65:H68) -> 122500 | L65: =SUM(I65:I68) -> 100312.5
B66: Moderate | C66: 120000 | D66: 0.5 | E66: =$D66*((1-E$65)/SUM($D$66:$D$68)) -> 0.3125 | F66: =$D66*((1-F$65)/SUM($D$66:$D$68)) -> 0.5625 | G66: =C66*E66 -> 37500 | H66: =C66*D66 -> 60000 | I66: =C66*F66 -> 67500
B67: Low | C67: 30000 | D67: 0.25 | E67: =$D67*((1-E$65)/SUM($D$66:$D$68)) -> 0.15625 | F67: =$D67*((1-F$65)/SUM($D$66:$D$68)) -> 0.28125 | G67: =C67*E67 -> 4687.5 | H67: =C67*D67 -> 7500 | I67: =C67*F67 -> 8437.5
B68: Total Loss | C68: -100000 | D68: 0.05 | E68: =$D68*((1-E$65)/SUM($D$66:$D$68)) -> 0.03125 | F68: =$D68*((1-F$65)/SUM($D$66:$D$68)) -> 0.05625 | G68: =C68*E68 -> -3125 | H68: =C68*D68 -> -5000 | I68: =C68*F68 -> -5625
A70: Portfolio | B70: Growth Outcome | C70: Payoff ($) | D70: Probability | E70: 30% + | F70: 30% - | G70: Average Payoff (30% +) | H70: Average Payoff (Actual) | I70: Average Payoff (30% -) | J70: Expected Payoff (30% +) | K70: Expected Payoff (Actual) | L70: Expected Payoff (30% -)
A71: B | B71: High | C71: 400000 | D71: 0.15 | E71: =D71+0.3 -> 0.45 | F71: =D71-0.1 -> 0.05 | G71: =C71*E71 -> 180000 | H71: =C71*D71 -> 60000 | I71: =C71*F71 -> 20000 | J71: =SUM(G71:G74) -> 231441.18 | K71: =SUM(H71:H74) -> 139500 | L71: =SUM(I71:I74) -> 108852.94
B72: Moderate | C72: 150000 | D72: 0.5 | E72: =$D72*((1-E$71)/SUM($D$72:$D$74)) -> 0.32352941 | F72: =$D72*((1-F$71)/SUM($D$72:$D$74)) -> 0.55882353 | G72: =C72*E72 -> 48529.412 | H72: =C72*D72 -> 75000 | I72: =C72*F72 -> 83823.529
B73: Low | C73: 50000 | D73: 0.25 | E73: =$D73*((1-E$71)/SUM($D$72:$D$74)) -> 0.16176471 | F73: =$D73*((1-F$71)/SUM($D$72:$D$74)) -> 0.27941176 | G73: =C73*E73 -> 8088.2353 | H73: =C73*D73 -> 12500 | I73: =C73*F73 -> 13970.588
B74: Total Loss | C74: -80000 | D74: 0.1 | E74: =$D74*((1-E$71)/SUM($D$72:$D$74)) -> 0.064705882 | F74: =$D74*((1-F$71)/SUM($D$72:$D$74)) -> 0.11176471 | G74: =C74*E74 -> -5176.4706 | H74: =C74*D74 -> -8000 | I74: =C74*F74 -> -8941.1765
A76: Portfolio | B76: Growth Outcome | C76: Payoff ($) | D76: Probability | E76: 30% + | F76: 30% - | G76: Average Payoff (30% +) | H76: Average Payoff (Actual) | I76: Average Payoff (30% -) | J76: Expected Payoff (30% +) | K76: Expected Payoff (Actual) | L76: Expected Payoff (30% -)
A77: C | B77: High | C77: 250000 | D77: 0.25 | E77: =D77+0.3 -> 0.55 | F77: =D77-0.1 -> 0.15 | G77: =C77*E77 -> 137500 | H77: =C77*D77 -> 62500 | I77: =C77*F77 -> 37500 | J77: =SUM(G77:G80) -> 162700 | K77: =SUM(H77:H80) -> 104500 | L77: =SUM(I77:I80) -> 85100
B78: Moderate | C78: 90000 | D78: 0.5 | E78: =$D78*((1-E$77)/SUM($D$78:$D$80)) -> 0.3 | F78: =$D78*((1-F$77)/SUM($D$78:$D$80)) -> 0.56666667 | G78: =C78*E78 -> 27000 | H78: =C78*D78 -> 45000 | I78: =C78*F78 -> 51000
B79: Low | C79: 20000 | D79: 0.15 | E79: =$D79*((1-E$77)/SUM($D$78:$D$80)) -> 0.09 | F79: =$D79*((1-F$77)/SUM($D$78:$D$80)) -> 0.17 | G79: =C79*E79 -> 1800 | H79: =C79*D79 -> 3000 | I79: =C79*F79 -> 3400
B80: Total Loss | C80: -60000 | D80: 0.1 | E80: =$D80*((1-E$77)/SUM($D$78:$D$80)) -> 0.06 | F80: =$D80*((1-F$77)/SUM($D$78:$D$80)) -> 0.11333333 | G80: =C80*E80 -> -3600 | H80: =C80*D80 -> -6000 | I80: =C80*F80 -> -6800
A83: 40% increase and decrease
A84: Portfolio | B84: Growth Outcome | C84: Payoff ($) | D84: Probability | E84: 40% + | F84: 40% - | G84: Average Payoff (40% +) | H84: Average Payoff (Actual) | I84: Average Payoff (40% -) | J84: Expected Payoff (40% +) | K84: Expected Payoff (Actual) | L84: Expected Payoff (40% -)
A85: A | B85: High | C85: 300000 | D85: 0.2 | E85: =D85+0.4 -> 0.6 | F85: =D85-0.1 -> 0.1 | G85: =C85*E85 -> 180000 | H85: =C85*D85 -> 60000 | I85: =C85*F85 -> 30000 | J85: =SUM(G85:G88) -> 211250 | K85: =SUM(H85:H88) -> 122500 | L85: =SUM(I85:I88) -> 100312.5
B86: Moderate | C86: 120000 | D86: 0.5 | E86: =$D86*((1-E$85)/SUM($D$86:$D$88)) -> 0.25 | F86: =$D86*((1-F$85)/SUM($D$86:$D$88)) -> 0.5625 | G86: =C86*E86 -> 30000 | H86: =C86*D86 -> 60000 | I86: =C86*F86 -> 67500
B87: Low | C87: 30000 | D87: 0.25 | E87: =$D87*((1-E$85)/SUM($D$86:$D$88)) -> 0.125 | F87: =$D87*((1-F$85)/SUM($D$86:$D$88)) -> 0.28125 | G87: =C87*E87 -> 3750 | H87: =C87*D87 -> 7500 | I87: =C87*F87 -> 8437.5
B88: Total Loss | C88: -100000 | D88: 0.05 | E88: =$D88*((1-E$85)/SUM($D$86:$D$88)) -> 0.025 | F88: =$D88*((1-F$85)/SUM($D$86:$D$88)) -> 0.05625 | G88: =C88*E88 -> -2500 | H88: =C88*D88 -> -5000 | I88: =C88*F88 -> -5625
A90: Portfolio | B90: Growth Outcome | C90: Payoff ($) | D90: Probability | E90: 40% + | F90: 40% - | G90: Average Payoff (40% +) | H90: Average Payoff (Actual) | I90: Average Payoff (40% -) | J90: Expected Payoff (40% +) | K90: Expected Payoff (Actual) | L90: Expected Payoff (40% -)
A91: B | B91: High | C91: 400000 | D91: 0.15 | E91: =D91+0.4 -> 0.55 | F91: =$D91*((1-F$25)/SUM($D$26:$D$28)) -> 0.16875 | G91: =C91*E91 -> 220000 | H91: =C91*D91 -> 60000 | I91: =C91*F91 -> 67500 | J91: =SUM(G91:G94) -> 262088.24 | K91: =SUM(H91:H94) -> 139500 | L91: =SUM(I91:I94) -> 145246.32
B92: Moderate | C92: 150000 | D92: 0.5 | E92: =$D92*((1-E$91)/SUM($D$92:$D$94)) -> 0.26470588 | F92: =$D92*((1-F$91)/SUM($D$92:$D$94)) -> 0.48897059 | G92: =C92*E92 -> 39705.882 | H92: =C92*D92 -> 75000 | I92: =C92*F92 -> 73345.588
B93: Low | C93: 50000 | D93: 0.25 | E93: =$D93*((1-E$91)/SUM($D$92:$D$94)) -> 0.13235294 | F93: =$D93*((1-F$91)/SUM($D$92:$D$94)) -> 0.24448529 | G93: =C93*E93 -> 6617.6471 | H93: =C93*D93 -> 12500 | I93: =C93*F93 -> 12224.265
B94: Total Loss | C94: -80000 | D94: 0.1 | E94: =$D94*((1-E$91)/SUM($D$92:$D$94)) -> 0.052941176 | F94: =$D94*((1-F$91)/SUM($D$92:$D$94)) -> 0.097794118 | G94: =C94*E94 -> -4235.2941 | H94: =C94*D94 -> -8000 | I94: =C94*F94 -> -7823.5294
A96: Portfolio | B96: Growth Outcome | C96: Payoff ($) | D96: Probability | E96: 40% + | F96: 40% - | G96: Average Payoff (40% +) | H96: Average Payoff (Actual) | I96: Average Payoff (40% -) | J96: Expected Payoff (40% +) | K96: Expected Payoff (Actual) | L96: Expected Payoff (40% -)
A97: C | B97: High | C97: 250000 | D97: 0.25 | E97: =D97+0.4 -> 0.65 | F97: =D97-0.1 -> 0.15 | G97: =C97*E97 -> 162500 | H97: =C97*D97 -> 62500 | I97: =C97*F97 -> 37500 | J97: =SUM(G97:G100) -> 182100 | K97: =SUM(H97:H100) -> 104500 | L97: =SUM(I97:I100) -> 85100
B98: Moderate | C98: 90000 | D98: 0.5 | E98: =$D98*((1-E$97)/SUM($D$98:$D$100)) -> 0.23333333 | F98: =$D98*((1-F$97)/SUM($D$98:$D$100)) -> 0.56666667 | G98: =C98*E98 -> 21000 | H98: =C98*D98 -> 45000 | I98: =C98*F98 -> 51000
B99: Low | C99: 20000 | D99: 0.15 | E99: =$D99*((1-E$97)/SUM($D$98:$D$100)) -> 0.07 | F99: =$D99*((1-F$97)/SUM($D$98:$D$100)) -> 0.17 | G99: =C99*E99 -> 1400 | H99: =C99*D99 -> 3000 | I99: =C99*F99 -> 3400
B100: Total Loss | C100: -60000 | D100: 0.1 | E100: =$D100*((1-E$97)/SUM($D$98:$D$100)) -> 0.046666667 | F100: =$D100*((1-F$97)/SUM($D$98:$D$100)) -> 0.11333333 | G100: =C100*E100 -> -2800 | H100: =C100*D100 -> -6000 | I100: =C100*F100 -> -6800
A103: 50% increase and decrease
A104: Portfolio | B104: Growth Outcome | C104: Payoff ($) | D104: Probability | E104: 50% + | F104: 50% - | G104: Average Payoff (50% +) | H104: Average Payoff (Actual) | I104: Average Payoff (50% -) | J104: Expected Payoff (50% +) | K104: Expected Payoff (Actual) | L104: Expected Payoff (50% -)
A105: A | B105: High | C105: 300000 | D105: 0.2 | E105: =D105+0.5 -> 0.7 | F105: =D105-0.5 -> -0.3 | G105: =C105*E105 -> 210000 | H105: =C105*D105 -> 60000 | I105: =C105*F105 -> -90000 | J105: =SUM(G105:G108) -> 233437.5 | K105: =SUM(H105:H108) -> 122500 | L105: =SUM(I105:I108) -> 11562.5
B106: Moderate | C106: 120000 | D106: 0.5 | E106: =$D106*((1-E$105)/SUM($D$106:$D$108)) -> 0.1875 | F106: =$D106*((1-F$105)/SUM($D$106:$D$108)) -> 0.8125 | G106: =C106*E106 -> 22500 | H106: =C106*D106 -> 60000 | I106: =C106*F106 -> 97500
B107: Low | C107: 30000 | D107: 0.25 | E107: =$D107*((1-E$105)/SUM($D$106:$D$108)) -> 0.09375 | F107: =$D107*((1-F$105)/SUM($D$106:$D$108)) -> 0.40625 | G107: =C107*E107 -> 2812.5 | H107: =C107*D107 -> 7500 | I107: =C107*F107 -> 12187.5
B108: Total Loss | C108: -100000 | D108: 0.05 | E108: =$D108*((1-E$105)/SUM($D$106:$D$108)) -> 0.01875 | F108: =$D108*((1-F$105)/SUM($D$106:$D$108)) -> 0.08125 | G108: =C108*E108 -> -1875 | H108: =C108*D108 -> -5000 | I108: =C108*F108 -> -8125
A110: Portfolio | B110: Growth Outcome | C110: Payoff ($) | D110: Probability | E110: 50% + | F110: 50% - | G110: Average Payoff (50% +) | H110: Average Payoff (Actual) | I110: Average Payoff (50% -) | J110: Expected Payoff (50% +) | K110: Expected Payoff (Actual) | L110: Expected Payoff (50% -)
A111: B | B111: High | C111: 400000 | D111: 0.15 | E111: =D111+0.5 -> 0.65 | F111: =$D111*((1-F$25)/SUM($D$26:$D$28)) -> 0.16875 | G111: =C111*E111 -> 260000 | H111: =C111*D111 -> 60000 | I111: =C111*F111 -> 67500 | J111: =SUM(G111:G114) -> 292735.29 | K111: =SUM(H111:H114) -> 139500 | L111: =SUM(I111:I114) -> 145246.32
B112: Moderate | C112: 150000 | D112: 0.5 | E112: =$D112*((1-E$111)/SUM($D$112:$D$114)) -> 0.20588235 | F112: =$D112*((1-F$111)/SUM($D$112:$D$114)) -> 0.48897059 | G112: =C112*E112 -> 30882.353 | H112: =C112*D112 -> 75000 | I112: =C112*F112 -> 73345.588
B113: Low | C113: 50000 | D113: 0.25 | E113: =$D113*((1-E$111)/SUM($D$112:$D$114)) -> 0.10294118 | F113: =$D113*((1-F$111)/SUM($D$112:$D$114)) -> 0.24448529 | G113: =C113*E113 -> 5147.0588 | H113: =C113*D113 -> 12500 | I113: =C113*F113 -> 12224.265
B114: Total Loss | C114: -80000 | D114: 0.1 | E114: =$D114*((1-E$111)/SUM($D$112:$D$114)) -> 0.041176471 | F114: =$D114*((1-F$111)/SUM($D$112:$D$114)) -> 0.097794118 | G114: =C114*E114 -> -3294.1176 | H114: =C114*D114 -> -8000 | I114: =C114*F114 -> -7823.5294
A116: Portfolio | B116: Growth Outcome | C116: Payoff ($) | D116: Probability | E116: 50% + | F116: 50% - | G116: Average Payoff (50% +) | H116: Average Payoff (Actual) | I116: Average Payoff (50% -) | J116: Expected Payoff (50% +) | K116: Expected Payoff (Actual) | L116: Expected Payoff (50% -)
A117: C | B117: High | C117: 250000 | D117: 0.25 | E117: =D117+0.5 -> 0.75 | F117: =D117-0.1 -> 0.15 | G117: =C117*E117 -> 187500 | H117: =C117*D117 -> 62500 | I117: =C117*F117 -> 37500 | J117: =SUM(G117:G120) -> 201500 | K117: =SUM(H117:H120) -> 104500 | L117: =SUM(I117:I120) -> 85100
B118: Moderate | C118: 90000 | D118: 0.5 | E118: =$D118*((1-E$117)/SUM($D$118:$D$120)) -> 0.16666667 | F118: =$D118*((1-F$117)/SUM($D$118:$D$120)) -> 0.56666667 | G118: =C118*E118 -> 15000 | H118: =C118*D118 -> 45000 | I118: =C118*F118 -> 51000
B119: Low | C119: 20000 | D119: 0.15 | E119: =$D119*((1-E$117)/SUM($D$118:$D$120)) -> 0.05 | F119: =$D119*((1-F$117)/SUM($D$118:$D$120)) -> 0.17 | G119: =C119*E119 -> 1000 | H119: =C119*D119 -> 3000 | I119: =C119*F119 -> 3400
B120: Total Loss | C120: -60000 | D120: 0.1 | E120: =$D120*((1-E$117)/SUM($D$118:$D$120)) -> 0.033333333 | F120: =$D120*((1-F$117)/SUM($D$118:$D$120)) -> 0.11333333 | G120: =C120*E120 -> -2000 | H120: =C120*D120 -> -6000 | I120: =C120*F120 -> -6800
A123: 60% increase and decrease
A124: Portfolio | B124: Growth Outcome | C124: Payoff ($) | D124: Probability | E124: 60% + | F124: 60% - | G124: Average Payoff (60% +) | H124: Average Payoff (Actual) | I124: Average Payoff (60% -) | J124: Expected Payoff (60% +) | K124: Expected Payoff (Actual) | L124: Expected Payoff (60% -)
A125: A | B125: High | C125: 300000 | D125: 0.2 | E125: =D125+0.6 -> 0.8 | F125: =D125-0.6 -> -0.4 | G125: =C125*E125 -> 240000 | H125: =C125*D125 -> 60000 | I125: =C125*F125 -> -120000 | J125: =SUM(G125:G128) -> 255625 | K125: =SUM(H125:H128) -> 122500 | L125: =SUM(I125:I128) -> -10625
...

Sheet Report
A1: Report
A3: 2. Discuss: (Approximately 20-30 lines in total)
A4: (a) interpret the implications of the average payoffs in terms of potential growth for the startup.
A5: Portfolio A offers substantial growth potential with an average payoff of $122,500, making it a good choice for startups. Portfolio B has the highest expected value of $139,500, offering higher growth potential. Portfolio C has the lowest projected value, with an average payback of $104,500, suggesting a less volatile approach. All three portfolios offer positive expected returns, with different levels of potential growth and risk. Portfolio B is the best choice for aggressive growth, while Portfolio A provides significant returns. Portfolio C offers the lowest returns and may be more suitable for a risk-averse investing approach. The startups should choose the portfolio that best fits their growth goals and risk tolerance.
A8: (b) how the Best and Worst-Case Scenarios for each portfolio could impact the startup's long-term strategy.
A9: Portfolio A
A10: Best case: payoff is 300,000 and its probability is 0.2 it is lower compare to other portfolio.
A11: Worse case : -100,000 total loss and its probability is low compare to other it is 0.05
A12: It is a moderate portfolio and can be one option for startup.
A14: Portfolio B
A15: Highest : payoff is 400,000 and its probability is 0.15 and expected payoff for this is also high 600,000, and it is highest potential payoff compare to other portfolio.
A16: Worse case: -80,000 total loss and its probability is 0.1 is high compare to A and same as C .
... A38: Which is the best portfolio, and why? (5-10 lines that explain how you arrived at the decision interpreting your analysis.)
B41: Expected Payoff: | C41: Standard Deviation (Risk): | D41: Best-Case Scenario: | E41: Worst-Case Scenario: | F41: Volatility:
A42: Portfolio A | B42: 122500 | C42: 98392.95 | D42: 300000 | E42: -100000 | F42: Moderate
A43: Portfolio B | B43: 139500 | C43: 130599.74 | D43: 400000 | E43: -80000 | F43: High
A44: Portfolio C | B44: 104500 | C44: 95754.34 | D44: 250000 | E44: -60000 | F44: Low
A47: According to our analysis, Portfolio B is the best portfolio.
A49: 1. Maximum Expected payoff: With an expected payoff of $139,500, Portfolio B has the maximum potential for growth.
A50: 2. Large Potential Returns: If the high-growth scenario comes to pass, Portfolio B has the potential to generate large financial gains based on the high projected payoff.
A51: 3. Risk Consideration: While Portfolio B has the maximum standard deviation ($130,599.74), which suggests a higher level of risk, this is reasonable for companies who are prepared to assume greater risk in exchange for big returns.
A52: 4. Strategic Fit for Aggressive Growth: A startup's goal of aggressive growth and market expansion is well matched with the large potential returns.
A53: 5. Risk-Return Balance: Portfolio B is a good option as it focuses on growth because its high volatile nature is acceptable as the returns are high
A54: 6. Worst-Case scenario: Although high loss is possible, the possibility of large return makes it worth the risk.
A55: 7. Opportunity Cost: If we select Portfolio B, it lowers the chance cost of deciding against the portfolio with the highest expected return.
A56: 8. Long-Term Strategy: The high possible profits provide support for long-term strategic goals like reinvestment, expansion, and achieving a larger market share.
A57: 9. Competitive Advantage: Higher returns on investment may provide a benefit over competitors by releasing up additional funds for research and development.
A58: 10. Growth Potential: Taking everything into account, Portfolio B helps the firm reach its goal of maximising its financial results and securing major expansion.
A61: 4. Sensitivity analysis
... A70: In 80% increase for Portfolio A, we have a probability of 1 for high growth and 0 for all the rest, resulting in zero payoffs for moderate, low and total loss scenarios

Sheet References
A1: Sr. No. | B1: References
A2: 1 | B2: Bobbitt, Z. (2021, September 3). How to calculate the variance of a probability distribution. Statology. https://www.statology.org/variance-of-probability-distribution/
A3: 2 | B3: Bloch, B. J. (2022a, May 9).How risky is your portfolio? Investopedia. https://www.investopedia.com/articles/pf/06/riskyportfolio.asp#:~:text=As%20a%20general%20rule%2C%20if,lose%20with%20a%20particular%20portfolio
A4: 3 | B4: McFarlane, G. (2023, December 11). The best portfolio balance. Investopedia. https://www.investopedia.com/financial-edge/0412/the-best-portfolio-balance.aspx
A5: 4 | B5: Kenton, W. (2024, June 27). What is sensitivity analysis? Investopedia. https://www.investopedia.com/terms/s/sensitivityanalysis.asp
A6: 5 | B6: https://chatgpt.com/
A7: 6 | B7: Corp, S. F. (2023, February 21). Investing if you are risk averse. Synovus. https://www.synovus.com/personal/resource-center/financial-newsletters/2022/september/investing-if-you-are-risk-averse/
